{
  "group-1742581004630": {
    "id": "group-1742581004630",
    "type": "group",
    "name": "Testing again",
    "participants": [
      "RobertTest",
      "Alice",
      "Bob",
      "Charlie",
      "David"
    ],
    "createdBy": "RobertTest",
    "createdAt": "2025-03-21T18:16:44.630Z"
  },
  "Alice-David": {
    "id": "Alice-David",
    "type": "direct",
    "participants": [
      "Alice",
      "David"
    ],
    "createdBy": "Alice",
    "createdAt": "2025-03-21T18:17:23.562Z"
  },
  "12345-Alice": {
    "id": "12345-Alice",
    "type": "direct",
    "participants": [
      "12345",
      "Alice"
    ],
    "createdBy": "12345",
    "createdAt": "2025-03-27T03:29:38.845Z"
  }
}